django_painless_seo-0.1.2.dist-info/DESCRIPTION.rst
django_painless_seo-0.1.2.dist-info/METADATA
django_painless_seo-0.1.2.dist-info/RECORD
django_painless_seo-0.1.2.dist-info/WHEEL
django_painless_seo-0.1.2.dist-info/metadata.json
django_painless_seo-0.1.2.dist-info/top_level.txt
painlessseo/__init__.py
painlessseo/admin.py
painlessseo/models.py
painlessseo/settings.py
painlessseo/templates/painlessseo/metadata.html
painlessseo/templatetags/__init__.py
painlessseo/templatetags/seo.py
