Metadata-Version: 2.0
Name: django-painless-seo
Version: 0.1.2
Summary: Painless SEO app for Django framework
Home-page: https://github.com/Glamping-Hub/django-painless-seo
Author: Glamping Hub
Author-email: it@glampinghub.com
License: BSD
Keywords: seo django
Platform: UNKNOWN
Classifier: Development Status :: 5 - Production/Stable
Classifier: Environment :: Web Environment
Classifier: Framework :: Django
Classifier: Intended Audience :: Developers
Classifier: License :: OSI Approved :: BSD License
Classifier: Operating System :: OS Independent
Classifier: Programming Language :: Python :: 2 :: Only
Classifier: Topic :: Software Development :: Libraries :: Python Modules
Classifier: Topic :: Internet
Requires: Django (>=1.5.0)
